bangla_normalizer/__init__.py
bangla_normalizer/conversion_data.py
bangla_normalizer/extractor.py
bangla_normalizer/methods.py
bangla_normalizer/normalizer.py
bangla_normalizer/utils.py
bangla_normalizer-0.1.1.dist-info/licenses/LICENSE.txt
bangla_normalizer-0.1.1.dist-info/METADATA
bangla_normalizer-0.1.1.dist-info/WHEEL
bangla_normalizer-0.1.1.dist-info/top_level.txt
bangla_normalizer-0.1.1.dist-info/RECORD
