Metadata-Version: 2.4
Name: bangla_normalizer
Version: 0.1.1
Summary: A Python library for normalizing Bengali text, including dates, numbers, currency, etc.
Home-page: https://github.com/shohanur-shoron/bangla_normalizer.git
Author: Md. Shohanur Rahman
Author-email: "Md. Shohanur Rahman" <shorons38@gmail.com>
Project-URL: Homepage, https://github.com/shohanur-shoron/bangla_normalizer.git
Project-URL: Bug Tracker, https://github.com/shohanur-shoron/bangla_normalizer/issues
Keywords: bengali,bangla,nlp,natural language processing,text normalization,text standardisation,bangla text processing,bengali text processing,text verbalization,spell-out,number to words,date to words,time to words,currency to words,taka normalization,percentage normalization,temperature normalization,ratio normalization,ordinal normalization,year normalization,phone number normalization,distance normalization,bangla nsw,bengali nsw,non-standard words,bangla tts,bengali tts,text to speech prep
Classifier: Development Status :: 3 - Alpha
Classifier: Intended Audience :: Developers
Classifier: Topic :: Text Processing :: Linguistic
Classifier: License :: OSI Approved :: MIT License
Classifier: Programming Language :: Python :: 3
Classifier: Programming Language :: Python :: 3.7
Classifier: Programming Language :: Python :: 3.8
Classifier: Programming Language :: Python :: 3.9
Classifier: Programming Language :: Python :: 3.10
Classifier: Programming Language :: Python :: 3.11
Classifier: Programming Language :: Python :: 3.12
Classifier: Programming Language :: Python :: 3.13
Classifier: Operating System :: OS Independent
Requires-Python: >=3.7
License-File: LICENSE.txt
Requires-Dist: regex
Requires-Dist: python-dateutil
Dynamic: author
Dynamic: home-page
Dynamic: license-file
Dynamic: requires-python
